LICENSE.txt
MANIFEST.in
README.md
VERSION
setup.py
strictyamljsonschema/__init__.py
strictyamljsonschema.egg-info/PKG-INFO
strictyamljsonschema.egg-info/SOURCES.txt
strictyamljsonschema.egg-info/dependency_links.txt
strictyamljsonschema.egg-info/not-zip-safe
strictyamljsonschema.egg-info/requires.txt
strictyamljsonschema.egg-info/top_level.txt