Metadata-Version: 2.1
Name: strictyamljsonschema
Version: 0.1.0
Summary: Create StrictYAML schemas from jsonschemas
Home-page: UNKNOWN
Author: Colm O'Connor
Author-email: colm.oconnor.github@gmail.com
License: MIT
Keywords: yaml
Platform: UNKNOWN
Classifier: Development Status :: 4 - Beta
Classifier: Intended Audience :: Developers
Classifier: License :: OSI Approved :: MIT License
Classifier: Topic :: Text Processing :: Markup
Classifier: Topic :: Software Development :: Libraries
Classifier: Natural Language :: English
Classifier: Programming Language :: Python :: 2
Classifier: Programming Language :: Python :: 2.6
Classifier: Programming Language :: Python :: 2.7
Classifier: Programming Language :: Python :: 3
Classifier: Programming Language :: Python :: 3.1
Classifier: Programming Language :: Python :: 3.2
Classifier: Programming Language :: Python :: 3.3
Classifier: Programming Language :: Python :: 3.4
Classifier: Programming Language :: Python :: 3.5
